sync_mailchimp_entra/__init__.py
sync_mailchimp_entra/__main__.py
sync_mailchimp_entra/core/graph.py
sync_mailchimp_entra/core/mailchimp.py
sync_mailchimp_entra/core/sync.py
sync_mailchimp_entra/scripts.py
sync_mailchimp_entra/utils/errors.py
sync_mailchimp_entra-1.3.0.dist-info/METADATA
sync_mailchimp_entra-1.3.0.dist-info/WHEEL
sync_mailchimp_entra-1.3.0.dist-info/RECORD
