Metadata-Version: 2.1
Name: sync_mailchimp_entra
Version: 1.3.0
Summary: A package to synchronize an Entra ID group with several Mailchimp contact lists.
Author: Armand Bouveron
Author-email: bouveron.armand@gmail.com
Requires-Python: >=3.10,<4.0
Classifier: Programming Language :: Python :: 3
Classifier: Programming Language :: Python :: 3.10
Classifier: Programming Language :: Python :: 3.11
Classifier: Programming Language :: Python :: 3.12
Requires-Dist: mailchimp-marketing (>=3.0.80,<3.1.0)
Requires-Dist: msgraph-sdk (>=1.4.0,<1.5.0)
